firecore/__init__.py
firecore/check.py
firecore/factory.py
firecore/import_utils.py
firecore/main_utils.py
firecore/numpy_ops.py
firecore/opencv_utils.py
firecore/params.py
firecore/system_utils.py
firecore/torch_utils.py
firecore/config/__init__.py
firecore/config/jsonnet.py
firecore/config/object_pool.py
firecore/config/types.py
firecore/data/__init__.py
firecore/data/datapipes.py
firecore/meters/__init__.py
firecore/meters/average.py
firecore/meters/base.py
firecore/testing/__init__.py
firecore/testing/loop.py
firecore/training/__init__.py
firecore/training/loop.py
firecore/utils/__init__.py
firecore/utils/distributed.py
firecore-0.6.1.dist-info/METADATA
firecore-0.6.1.dist-info/WHEEL
firecore-0.6.1.dist-info/entry_points.txt
firecore-0.6.1.dist-info/licenses/LICENSE
firecore-0.6.1.dist-info/RECORD
