Metadata-Version: 2.3
Name: firecore
Version: 0.6.1
Summary: Framework for fast and reproducable deep learning experiments
Author-email: SunDoge <triplez0@outlook.com>
License-File: LICENSE
Requires-Python: >=3.10
Requires-Dist: loguru>=0.7
Requires-Dist: numpy>=1
Requires-Dist: pydantic>=2.8
Requires-Dist: rjsonnet>=0.5.4
